<annotation>
	<folder>image166_jar</folder>
	<filename>image_861.jpg</filename>
	<path>/home/afzal/JAR/image166_jar/image_861.jpg</path>
	<source>
		<database>Unknown</database>
	</source>
	<size>
		<width>1076</width>
		<height>740</height>
		<depth>3</depth>
	</size>
	<segmented>0</segmented>
	<object>
		<name>JAR</name>
		<pose>Unspecified</pose>
		<truncated>0</truncated>
		<difficult>0</difficult>
		<bndbox>
			<xmin>7</xmin>
			<ymin>204</ymin>
			<xmax>350</xmax>
			<ymax>711</ymax>
		</bndbox>
	</object>
	<object>
		<name>JAR</name>
		<pose>Unspecified</pose>
		<truncated>0</truncated>
		<difficult>0</difficult>
		<bndbox>
			<xmin>354</xmin>
			<ymin>195</ymin>
			<xmax>704</xmax>
			<ymax>721</ymax>
		</bndbox>
	</object>
	<object>
		<name>JAR</name>
		<pose>Unspecified</pose>
		<truncated>0</truncated>
		<difficult>0</difficult>
		<bndbox>
			<xmin>708</xmin>
			<ymin>203</ymin>
			<xmax>1059</xmax>
			<ymax>713</ymax>
		</bndbox>
	</object>
</annotation>
